basic_pitch/__init__.py
basic_pitch/callbacks.py
basic_pitch/commandline_printing.py
basic_pitch/constants.py
basic_pitch/inference.py
basic_pitch/models.py
basic_pitch/nn.py
basic_pitch/note_creation.py
basic_pitch/predict.py
basic_pitch/train.py
basic_pitch/visualize.py
basic_pitch/data/README.md
basic_pitch/data/__init__.py
basic_pitch/data/commandline.py
basic_pitch/data/download.py
basic_pitch/data/pipeline.py
basic_pitch/data/tf_example_deserialization.py
basic_pitch/data/tf_example_serialization.py
basic_pitch/data/datasets/__init__.py
basic_pitch/data/datasets/guitarset.py
basic_pitch/data/datasets/ikala.py
basic_pitch/data/datasets/maestro.py
basic_pitch/data/datasets/medleydb_pitch.py
basic_pitch/data/datasets/slakh.py
basic_pitch/layers/__init__.py
basic_pitch/layers/math.py
basic_pitch/layers/nnaudio.py
basic_pitch/layers/signal.py
basic_pitch/saved_models/icassp_2022/nmp.onnx
basic_pitch/saved_models/icassp_2022/nmp.tflite
basic_pitch/saved_models/icassp_2022/nmp/saved_model.pb
basic_pitch/saved_models/icassp_2022/nmp/variables/variables.data-00000-of-00001
basic_pitch/saved_models/icassp_2022/nmp/variables/variables.index
basic_pitch/saved_models/icassp_2022/nmp.mlpackage/Manifest.json
basic_pitch/saved_models/icassp_2022/nmp.mlpackage/Data/com.apple.CoreML/model.mlmodel
basic_pitch/saved_models/icassp_2022/nmp.mlpackage/Data/com.apple.CoreML/weights/weight.bin
basic_pitch-0.4.0.dist-info/LICENSE
basic_pitch-0.4.0.dist-info/METADATA
basic_pitch-0.4.0.dist-info/NOTICE
basic_pitch-0.4.0.dist-info/WHEEL
basic_pitch-0.4.0.dist-info/entry_points.txt
basic_pitch-0.4.0.dist-info/top_level.txt
basic_pitch-0.4.0.dist-info/RECORD
